solo_mcp/__init__.py
solo_mcp/config.py
solo_mcp/mcp_server.py
solo_mcp/server.py
solo_mcp/tools/__init__.py
solo_mcp/tools/adaptive.py
solo_mcp/tools/context.py
solo_mcp/tools/credits.py
solo_mcp/tools/fs.py
solo_mcp/tools/index.py
solo_mcp/tools/learning.py
solo_mcp/tools/memory.py
solo_mcp/tools/orchestrator.py
solo_mcp/tools/proc.py
solo_mcp/tools/roles.py
solo_mcp/utils/__init__.py
solo_mcp/utils/file_utils.py
solo_mcp/utils/search_utils.py
solo_mcp-0.1.1.dist-info/licenses/LICENSE
solo_mcp-0.1.1.dist-info/METADATA
solo_mcp-0.1.1.dist-info/WHEEL
solo_mcp-0.1.1.dist-info/entry_points.txt
solo_mcp-0.1.1.dist-info/top_level.txt
solo_mcp-0.1.1.dist-info/RECORD
