Metadata-Version: 2.4
Name: solo-mcp
Version: 0.1.1
Summary: 智能代理协作平台 - 基于 MCP 协议的多角色任务编排系统
Home-page: https://github.com/your-username/solo-mcp
Author: Solo MCP Team
Author-email: Solo MCP Team <contact@solo-mcp.dev>
Maintainer-email: Solo MCP Team <contact@solo-mcp.dev>
License: Apache-2.0
Project-URL: Homepage, https://github.com/your-username/solo-mcp
Project-URL: Bug Reports, https://github.com/your-username/solo-mcp/issues
Project-URL: Source, https://github.com/your-username/solo-mcp
Project-URL: Documentation, https://solo-mcp.readthedocs.io/
Keywords: mcp,ai,agent,orchestration,memory,context
Classifier: Development Status :: 3 - Alpha
Classifier: Intended Audience :: Developers
Classifier: License :: OSI Approved :: Apache Software License
Classifier: Operating System :: OS Independent
Classifier: Programming Language :: Python :: 3
Classifier: Programming Language :: Python :: 3.11
Classifier: Programming Language :: Python :: 3.12
Classifier: Topic :: Software Development :: Libraries :: Python Modules
Classifier: Topic :: Scientific/Engineering :: Artificial Intelligence
Requires-Python: >=3.11
License-File: LICENSE
Requires-Dist: mcp[cli]>=1.4.0
Requires-Dist: sentence-transformers>=2.7.0
Requires-Dist: requests>=2.31.0
Requires-Dist: pytest>=7.4.0
Requires-Dist: pytest-asyncio>=0.21.0
Requires-Dist: black>=23.0.0
Requires-Dist: mcp-feedback-enhanced>=0.0.1
Provides-Extra: dev
Requires-Dist: pytest>=7.0.0; extra == "dev"
Requires-Dist: pytest-cov>=4.0.0; extra == "dev"
Requires-Dist: black>=23.0.0; extra == "dev"
Requires-Dist: flake8>=6.0.0; extra == "dev"
Requires-Dist: mypy>=1.0.0; extra == "dev"
Provides-Extra: docs
Requires-Dist: sphinx>=5.0.0; extra == "docs"
Requires-Dist: sphinx-rtd-theme>=1.0.0; extra == "docs"
Dynamic: author
Dynamic: home-page
Dynamic: license-file
Dynamic: requires-python
